bno055_usb_stick_py/97-ttyacm.rules
bno055_usb_stick_py/__init__.py
bno055_usb_stick_py/bno055.json
bno055_usb_stick_py/bno055.py
bno055_usb_stick_py/bno055_usb_stick.py
bno055_usb_stick_py/disable_modem_manager_bno_usb_stick.py
bno055_usb_stick_py/examples.py
bno055_usb_stick_py-0.9.5.dist-info/LICENSE
bno055_usb_stick_py-0.9.5.dist-info/METADATA
bno055_usb_stick_py-0.9.5.dist-info/WHEEL
bno055_usb_stick_py-0.9.5.dist-info/top_level.txt
bno055_usb_stick_py-0.9.5.dist-info/RECORD
