Metadata-Version: 2.1
Name: bno055-usb-stick-py
Version: 0.9.5
Summary: BNO055 USB Stick Linux Python Driver
Home-page: https://github.com/selyunin/bno055_usb_stick_py
Author: Dr. Konstantin Selyunin
Author-email: selyunin.k.v@gmail.com
License: MIT
Platform: UNKNOWN
Classifier: Programming Language :: Python :: 3
Classifier: License :: OSI Approved :: MIT License
Classifier: Operating System :: POSIX
Requires: pyudev
Requires: pyserial
Requires: dataclasses
Requires-Dist: pyserial
Requires-Dist: pyudev
Requires-Dist: dataclasses
